ashlarUC2/__init__.py
ashlarUC2/_version.py
ashlarUC2/filepattern.py
ashlarUC2/fileseries.py
ashlarUC2/reg.py
ashlarUC2/thumbnail.py
ashlarUC2/transform.py
ashlarUC2/utils.py
ashlarUC2/viewer.py
ashlarUC2/zen.py
ashlarUC2/scripts/__init__.py
ashlarUC2/scripts/ashlar.py
ashlarUC2/scripts/make_alignment_movie.py
ashlarUC2/scripts/preview_slide.py
ashlaruc2-1.18.4.dist-info/licenses/LICENSE
ashlaruc2-1.18.4.dist-info/METADATA
ashlaruc2-1.18.4.dist-info/WHEEL
ashlaruc2-1.18.4.dist-info/top_level.txt
ashlaruc2-1.18.4.dist-info/RECORD
