Metadata-Version: 2.4
Name: ashlarUC2
Version: 1.18.4
Summary: Alignment by Simultaneous Harmonization of Layer/Adjacency Registration
Home-page: https://github.com/openuc2/ashlar
Download-URL: https://github.com/openuc2/ashlar/archive/v1.18.4.tar.gz
Author: Jeremy Muhlich modified by Benedict Diederich
Author-email: benedictdied@gmail.com
License: MIT License
Keywords: scripts,microscopy,registration,stitching
Classifier: Development Status :: 5 - Production/Stable
Classifier: Intended Audience :: End Users/Desktop
Classifier: Intended Audience :: Science/Research
Classifier: License :: OSI Approved :: MIT License
Classifier: Natural Language :: English
Classifier: Operating System :: OS Independent
Classifier: Programming Language :: Python :: 3
Classifier: Topic :: Scientific/Engineering :: Visualization
License-File: LICENSE
Requires-Dist: numpy>=1.18.1
Requires-Dist: matplotlib>=3.1.2
Requires-Dist: networkx>=2.4
Requires-Dist: scipy>=1.4.1
Requires-Dist: scikit-image>=0.19.2
Requires-Dist: scikit-learn>=0.21.1
Requires-Dist: tifffile>=2023.3.15
Requires-Dist: zarr>=2.11.3
Requires-Dist: blessed>=1.17
Dynamic: author
Dynamic: author-email
Dynamic: classifier
Dynamic: description
Dynamic: description-content-type
Dynamic: download-url
Dynamic: home-page
Dynamic: keywords
Dynamic: license
Dynamic: license-file
Dynamic: requires-dist
Dynamic: summary
